bolster-0.4.0.dist-info/METADATA
bolster-0.4.0.dist-info/WHEEL
bolster-0.4.0.dist-info/entry_points.txt
bolster-0.4.0.dist-info/licenses/LICENSE
bolster/__init__.py
bolster/cli.py
bolster/data_sources/__init__.py
bolster/data_sources/cineworld.py
bolster/data_sources/companies_house.py
bolster/data_sources/eoni.py
bolster/data_sources/metoffice.py
bolster/data_sources/ni_house_price_index.py
bolster/data_sources/ni_water.py
bolster/data_sources/wikipedia.py
bolster/stats/__init__.py
bolster/stats/distributions.py
bolster/utils/__init__.py
bolster/utils/aws/__init__.py
bolster/utils/azure/__init__.py
bolster/utils/deco.py
bolster/utils/dt.py
bolster/utils/io.py
bolster/utils/web.py
bolster-0.4.0.dist-info/RECORD
