Metadata-Version: 2.1
Name: bolster
Version: 0.4.0
Summary: Bolster's Brain, you've been warned
Keywords: bolster,api,data science,data,data engineering,data analysis,data pipeline,data processing,data wrangling,data transformation,cli,command line interface,python
Author-Email: Andrew Bolster <andrew.bolster@gmail.com>
Classifier: Development Status :: 2 - Pre-Alpha
Classifier: Intended Audience :: Developers
Classifier: License :: OSI Approved :: GNU General Public License v3 (GPLv3)
Classifier: Natural Language :: English
Classifier: Programming Language :: Python :: 3
Classifier: Programming Language :: Python :: 3.9
Classifier: Programming Language :: Python :: 3.10
Classifier: Programming Language :: Python :: 3.11
Classifier: Programming Language :: Python :: 3.12
Project-URL: Homepage, https://github.com/andrewbolster/bolster
Project-URL: Documentation, https://bolster.readthedocs.io
Project-URL: Repository, https://github.com/andrewbolster/bolster.git
Project-URL: Bug Tracker, https://github.com/andrewbolster/bolster/issues
Requires-Python: <4.0,>=3.9
Requires-Dist: boto3>=1.37.37
Requires-Dist: bs4>=0.0.2
Requires-Dist: click>=8.1.8
Requires-Dist: click-log>=0.4.0
Requires-Dist: dateparser>=1.2.1
Requires-Dist: lxml>=5.3.2
Requires-Dist: numpy<2.0,>=1.25.0
Requires-Dist: openpyxl>=3.1.5
Requires-Dist: pandas>=2.0.3
Requires-Dist: pillow>=10.4.0
Requires-Dist: psycopg2-binary>=2.9.10
Requires-Dist: pytest-cov>=5.0.0
Requires-Dist: requests>=2.32.3
Requires-Dist: requests-cache>=1.2.1
Requires-Dist: scipy>=1.10.1
Requires-Dist: tqdm>=4.67.1
Requires-Dist: waybackpy>=3.0.6
Requires-Dist: xlrd>=2.0.1
